shellm/__init__.py
shellm/__main__.py
shellm/__version__.py
shellm/app.py
shellm/cache.py
shellm/config.py
shellm/function.py
shellm/integration.py
shellm/printer.py
shellm/role.py
shellm/utils.py
shellm/handlers/__init__.py
shellm/handlers/chat_handler.py
shellm/handlers/default_handler.py
shellm/handlers/handler.py
shellm/handlers/multiscript_handler.py
shellm/handlers/repl_handler.py
shellm/llm_functions/__init__.py
shellm/llm_functions/init_functions.py
shellm/llm_functions/common/execute_shell.py
shellm/llm_functions/mac/apple_script.py
shellm_cli-1.3.6.dist-info/METADATA
shellm_cli-1.3.6.dist-info/WHEEL
shellm_cli-1.3.6.dist-info/entry_points.txt
shellm_cli-1.3.6.dist-info/licenses/LICENSE
shellm_cli-1.3.6.dist-info/RECORD
